diffhouse/__init__.py
diffhouse/api/__init__.py
diffhouse/api/exceptions.py
diffhouse/api/extractor.py
diffhouse/api/repo.py
diffhouse/constants.py
diffhouse/entities/__init__.py
diffhouse/entities/branch.py
diffhouse/entities/commit.py
diffhouse/entities/diff.py
diffhouse/entities/filemod.py
diffhouse/entities/git_object.py
diffhouse/entities/tag.py
diffhouse/git/__init__.py
diffhouse/git/cli.py
diffhouse/git/cloning.py
diffhouse/pipelines/__init__.py
diffhouse/pipelines/branch_pipeline.py
diffhouse/pipelines/commit_pipeline.py
diffhouse/pipelines/constants.py
diffhouse/pipelines/diff_pipeline.py
diffhouse/pipelines/file_mod_pipeline.py
diffhouse/pipelines/tag_pipeline.py
diffhouse/pipelines/utils.py
diffhouse/utils/__init__.py
diffhouse/utils/cleanup.py
diffhouse-2.0.2.dist-info/licenses/LICENSE.md
diffhouse-2.0.2.dist-info/WHEEL
diffhouse-2.0.2.dist-info/METADATA
diffhouse-2.0.2.dist-info/RECORD
