Metadata-Version: 2.4
Name: diffhouse
Version: 2.0.2
Summary: Repository mining tool for structuring Git metadata at scale.
License-Expression: MIT
License-File: LICENSE.md
Classifier: Programming Language :: Python :: 3
Classifier: Operating System :: OS Independent
Requires-Dist: packaging>=25.0
Requires-Dist: regex>=2025.9.18
Requires-Dist: validators>=0.35.0
Requires-Dist: xxhash>=3.6.0
Requires-Dist: pandas>=2.0.0 ; extra == 'pandas'
Requires-Dist: polars>=1.0.0 ; extra == 'polars'
Requires-Python: >=3.10
Project-URL: Documentation, https://vupdivup.github.io/diffhouse/
Project-URL: Repository, https://github.com/vupdivup/diffhouse
Provides-Extra: pandas
Provides-Extra: polars
